appkit/__init__.py
appkit/apps.py
appkit/debug.py
appkit/handlers.py
appkit/managers.py
appkit/models.py
appkit/notification.py
appkit/settings.py
appkit/shortcuts.py
appkit/storages.py
appkit/tests.py
appkit/transformers.py
appkit/util.py
appkit/views.py
appkit/api/__init__.py
appkit/api/filters.py
appkit/api/mixins.py
appkit/api/pagination.py
appkit/api/relations.py
appkit/api/renderers.py
appkit/api/serializers.py
appkit/api/tests.py
appkit/api/views.py
appkit/auth/__init__.py
appkit/auth/backends.py
appkit/auth/decorators.py
appkit/auth/email.py
appkit/auth/permissions.py
appkit/drf/__init__.py
appkit/drf/adapters.py
appkit/drf/authentication.py
appkit/drf/backends.py
appkit/drf/endpoints.py
appkit/drf/exceptions.py
appkit/drf/fields.py
appkit/drf/filters.py
appkit/drf/mixins.py
appkit/drf/permissions.py
appkit/drf/serializers.py
appkit/drf_appkit.egg-info/PKG-INFO
appkit/drf_appkit.egg-info/SOURCES.txt
appkit/drf_appkit.egg-info/dependency_links.txt
appkit/drf_appkit.egg-info/top_level.txt
appkit/forms/__init__.py
appkit/forms/widgets.py
appkit/jinja2/appkit/forms/widgets/money_widget.html
appkit/migrations/0001_initial.py
appkit/migrations/0002_arrangement_tags.py
appkit/migrations/0003_auto_20210221_0852.py
appkit/migrations/0004_auto_20210309_0655.py
appkit/migrations/0005_auto_20210324_1046.py
appkit/migrations/0006_sitealias.py
appkit/migrations/0007_auto_20211021_1901.py
appkit/migrations/0008_update_autofields.py
appkit/migrations/0009_alter_arrangement_unique_together_and_more.py
appkit/migrations/0010_arrangement_name.py
appkit/migrations/0011_alter_sitealias_options.py
appkit/migrations/0012_alter_sitealias_site.py
appkit/migrations/0013_usergroup.py
appkit/migrations/0014_remove_note_notes_note_content_type_note_object_id.py
appkit/migrations/0015_alter_note_content_type_alter_note_object_id.py
appkit/migrations/0016_alter_arrangementitem_unique_together_and_more.py
appkit/migrations/0017_alter_imageattachment_image.py
appkit/migrations/0018_place_geoposition.py
appkit/migrations/0019_alter_place_geoposition.py
appkit/migrations/0020_remove_arrangement_type_arrangement_content_type.py
drf_appkit-1.6.6.dist-info/METADATA
drf_appkit-1.6.6.dist-info/WHEEL
drf_appkit-1.6.6.dist-info/top_level.txt
drf_appkit-1.6.6.dist-info/RECORD
